examples/__init__.py
examples/node2vec_example.py
gnne/__init__.py
gnne/graphs/__init__.py
gnne/graphs/core.py
gnne/models/__init__.py
gnne/models/graph2vec.py
gnne/models/node2vec.py
gnne/utils/__init__.py
gnne/utils/data_utils.py
gnne/utils/sampling_methods.py
utils/__init__.py
utils/data_utils.py
utils/sampling_methods.py
gnne-0.0.4.dist-info/LICENSE
gnne-0.0.4.dist-info/METADATA
gnne-0.0.4.dist-info/WHEEL
gnne-0.0.4.dist-info/top_level.txt
gnne-0.0.4.dist-info/RECORD
